magicfiles/__init__.py
magicfiles/test.py
magicfiles-1.0.0.dist-info/licenses/LICENSE
magicfiles-1.0.0.dist-info/METADATA
magicfiles-1.0.0.dist-info/WHEEL
magicfiles-1.0.0.dist-info/top_level.txt
magicfiles-1.0.0.dist-info/RECORD
