Metadata-Version: 2.4
Name: magicfiles
Version: 1.0.0
Summary: A simple powerfull module for files handling
Home-page: https://github.com/0xF55/magicfiles
Author: 0xF55
Classifier: Programming Language :: Python :: 3
Classifier: License :: OSI Approved :: MIT License
Classifier: Operating System :: OS Independent
Requires-Python: >=3.6
License-File: LICENSE
Dynamic: author
Dynamic: classifier
Dynamic: description
Dynamic: description-content-type
Dynamic: home-page
Dynamic: license-file
Dynamic: requires-python
Dynamic: summary
